MANIFEST.in
README.rst
VERSION
setup.cfg
setup.py
glit/__init__.py
glit/all_command.py
glit/cli.py
glit/clone_all_command.py
glit/clone_command.py
glit/clone_set_command.py
glit/config.py
glit/config_command.py
glit/git.py
glit/gitstorage.py
glit/localstorage.py
glit/repo.py
glit/utils.py
glit.egg-info/PKG-INFO
glit.egg-info/SOURCES.txt
glit.egg-info/dependency_links.txt
glit.egg-info/entry_points.txt
glit.egg-info/requires.txt
glit.egg-info/top_level.txt