Metadata-Version: 1.1
Name: glit
Version: 0.21
Summary: Clones sets of git repositories
Home-page: https://github.com/vandmo/glit
Author: vandmo
Author-email: mikael@vandmo.se
License: Apache License 2.0
Platform: UNKNOWN
Classifier: Development Status :: 2 - Pre-Alpha
Classifier: Intended Audience :: Developers
Classifier: License :: OSI Approved :: Apache Software License
Classifier: Operating System :: OS Independent
Classifier: Programming Language :: Python
Classifier: Programming Language :: Python :: 3
Classifier: Programming Language :: Python :: 3.6
